sakepedia/SakeData.py
sakepedia/SakepediaAPI.py
sakepedia/__init__.py
sakepedia-0.1.1.dist-info/LICENSE
sakepedia-0.1.1.dist-info/METADATA
sakepedia-0.1.1.dist-info/WHEEL
sakepedia-0.1.1.dist-info/top_level.txt
sakepedia-0.1.1.dist-info/RECORD
