Metadata-Version: 2.1
Name: sakepedia
Version: 0.1.1
Summary: sakepedia: Sakepedia API
Home-page: https://www.code4sake.org/
Download-URL: https://github.com/Code-for-SAKE/SakepediaSDK
Author: Code for SAKE
Maintainer: Code for SAKE
License: MIT License
Platform: UNKNOWN
Classifier: License :: OSI Approved :: MIT License
Classifier: Programming Language :: Python :: 3
Classifier: Programming Language :: Python :: 3.6
Classifier: Programming Language :: Python :: 3.7
Classifier: Programming Language :: Python :: 3.8
Classifier: Programming Language :: Python :: 3.9
Classifier: Programming Language :: Python :: 3 :: Only
Requires-Python: >=3.6
License-File: LICENSE
Requires-Dist: urllib3 (>=1.24.3)
Requires-Dist: jsonschema (>=4.3.3)
Requires-Dist: bs4 (>=0.0.1)
